kartograf/__init__.py
kartograf-1.0.2.dist-info/METADATA
kartograf-1.0.2.dist-info/WHEEL
kartograf-1.0.2.dist-info/top_level.txt
kartograf-1.0.2.dist-info/RECORD
