Metadata-Version: 2.4
Name: kartograf
Version: 1.0.2
Summary: Please use conda-forge to install kartograf
Author-email: Mike Henry <mike.henry@omsf.io>
License-Expression: MIT
Requires-Python: >=3.7
